{
    "logs": [
        {
            "comment": "test comment",
            "reply": "test reply",
            "ratio": "test ratio",
            "time": "time test",
            "season": "season test",
            "episode": "episode test",
            "comment_id": "0"
        },
        {
            "comment": "I've heard it said that if you don't know a Michael Scott, you *are* a Michael Scott",
            "reply": "So, do you know what you're gonna say when he shows up?",
            "ratio": 51,
            "time": "29/12/2020 21:44:42",
            "season": 9,
            "episode": 23,
            "comment_id": "ghh0vmp"
        },
        {
            "comment": "I would rather be Michael than Jim. I guess that makes me a Dwight?",
            "reply": "Correction. Just you. Alright, meeting. Multi-function room.",
            "ratio": 52,
            "time": "29/12/2020 23:09:15",
            "season": 7,
            "episode": 19,
            "comment_id": "ghh66un"
        }
    ]
}